estecopy/__init__.py
estecopy/charts.py
estecopy/info.py
estecopy/plan.py
estecopy/rsm.py
estecopy/_internal/_charts.py
estecopy/_internal/_db.py
estecopy/_internal/_info.py
estecopy/_internal/_plan.py
estecopy/_internal/_rsm.py
estecopy/_internal/utils/config.py
estecopy/_internal/utils/connection.py
estecopy/_internal/utils/greet_server.py
estecopy/_internal/utils/locks.py
estecopy/_internal/utils/log.py
estecopy/_internal/utils/server_validation.py
estecopy/_utils/arg_parse.py
estecopy/_utils/python_rsm.py
estecopy/db/__init__.py
estecopy/db/_internal/attributes.py
estecopy/db/_internal/design_table.py
estecopy/db/_internal/design_table_encoder.py
estecopy/db/_internal/encoded_header_table_builder.py
estecopy/db/_internal/progress_loader.py
estecopy/db/_internal/shapes.py
estecopy/db/_internal/simple_table_builder.py
estecopy/db/_internal/symbol_converter.py
estecopy/db/_internal/table_data_checker.py
estecopy-2.1.0.dist-info/licenses/LICENSE
pyfrontier/__init__.py
pyfrontier/_internal/config.py
estecopy-2.1.0.dist-info/METADATA
estecopy-2.1.0.dist-info/WHEEL
estecopy-2.1.0.dist-info/top_level.txt
estecopy-2.1.0.dist-info/RECORD
