Metadata-Version: 2.4
Name: estecopy
Version: 2.1.0
Summary: Python library to support the proprietary modeFRONTER software
Home-page: https://www.esteco.com
Author: ESTECO
Author-email: python.software@esteco.com
Keywords: estecopy,ESTECO,modeFRONTIER,pyFRONTIER,optimization
Classifier: Development Status :: 5 - Production/Stable
Classifier: Programming Language :: Python :: 3
Classifier: License :: OSI Approved :: MIT License
Classifier: Operating System :: Microsoft :: Windows
Classifier: Operating System :: MacOS
Classifier: Operating System :: Unix
Classifier: Operating System :: POSIX
Classifier: Topic :: Scientific/Engineering
Classifier: Topic :: Software Development
Classifier: Topic :: Office/Business
Requires-Python: >=3.8
License-File: LICENSE
Dynamic: license-file
